NViXTTS/VERSION
NViXTTS/__init__.py
NViXTTS/api.py
NViXTTS/model.py
NViXTTS/bin/__init__.py
NViXTTS/bin/collect_env_info.py
NViXTTS/bin/compute_attention_masks.py
NViXTTS/bin/compute_embeddings.py
NViXTTS/bin/compute_statistics.py
NViXTTS/bin/eval_encoder.py
NViXTTS/bin/extract_tts_spectrograms.py
NViXTTS/bin/find_unique_chars.py
NViXTTS/bin/find_unique_phonemes.py
NViXTTS/bin/remove_silence_using_vad.py
NViXTTS/bin/resample.py
NViXTTS/bin/synthesize.py
NViXTTS/bin/train_encoder.py
NViXTTS/bin/train_tts.py
NViXTTS/bin/train_vocoder.py
NViXTTS/bin/tune_wavegrad.py
NViXTTS/config/__init__.py
NViXTTS/config/shared_configs.py
NViXTTS/encoder/__init__.py
NViXTTS/encoder/dataset.py
NViXTTS/encoder/losses.py
NViXTTS/encoder/models/__init__.py
NViXTTS/encoder/models/base_encoder.py
NViXTTS/encoder/models/lstm.py
NViXTTS/encoder/models/resnet.py
NViXTTS/encoder/utils/__init__.py
NViXTTS/encoder/utils/generic_utils.py
NViXTTS/encoder/utils/prepare_voxceleb.py
NViXTTS/encoder/utils/training.py
NViXTTS/encoder/utils/visual.py
NViXTTS/server/__init__.py
NViXTTS/server/server.py
NViXTTS/tts/__init__.py
NViXTTS/tts/configs/__init__.py
NViXTTS/tts/configs/align_tts_config.py
NViXTTS/tts/configs/bark_config.py
NViXTTS/tts/configs/delightful_tts_config.py
NViXTTS/tts/configs/fast_pitch_config.py
NViXTTS/tts/configs/fast_speech_config.py
NViXTTS/tts/configs/fastspeech2_config.py
NViXTTS/tts/configs/glow_tts_config.py
NViXTTS/tts/configs/neuralhmm_tts_config.py
NViXTTS/tts/configs/overflow_config.py
NViXTTS/tts/configs/shared_configs.py
NViXTTS/tts/configs/speedy_speech_config.py
NViXTTS/tts/configs/tacotron2_config.py
NViXTTS/tts/configs/tacotron_config.py
NViXTTS/tts/configs/tortoise_config.py
NViXTTS/tts/configs/vits_config.py
NViXTTS/tts/configs/xtts_config.py
NViXTTS/tts/datasets/__init__.py
NViXTTS/tts/datasets/dataset.py
NViXTTS/tts/datasets/formatters.py
NViXTTS/tts/layers/__init__.py
NViXTTS/tts/layers/losses.py
NViXTTS/tts/layers/align_tts/__init__.py
NViXTTS-0.0.2.dist-info/LICENSE.txt
NViXTTS-0.0.2.dist-info/METADATA
NViXTTS-0.0.2.dist-info/WHEEL
NViXTTS-0.0.2.dist-info/entry_points.txt
NViXTTS-0.0.2.dist-info/top_level.txt
NViXTTS-0.0.2.dist-info/RECORD
