Metadata-Version: 2.1
Name: NViXTTS
Version: 0.0.2
Summary: Deep learning for Vietnamese Text to Speech
Home-page: https://github.com/iris-mygh/NViXTTS_pl
Author: Iris
Author-email: irisle.cv@gmail.com
License: MIT
Classifier: Programming Language :: Python
Classifier: Programming Language :: Python :: 3
Classifier: Programming Language :: Python :: 3.9
Classifier: Programming Language :: Python :: 3.10
Classifier: Programming Language :: Python :: 3.11
Requires-Python: >=3.9.0, <3.12
License-File: LICENSE.txt
Requires-Dist: cython >=0.29.30
Requires-Dist: scipy >=1.11.2
Requires-Dist: torch >=2.1
Requires-Dist: torchaudio
Requires-Dist: soundfile >=0.12.0
Requires-Dist: librosa >=0.10.0
Requires-Dist: scikit-learn >=1.3.0
Requires-Dist: inflect >=5.6.0
Requires-Dist: tqdm >=4.64.1
Requires-Dist: anyascii >=0.3.0
Requires-Dist: pyyaml >=6.0
Requires-Dist: fsspec >=2023.6.0
Requires-Dist: aiohttp >=3.8.1
Requires-Dist: packaging >=23.1
Requires-Dist: mutagen ==1.47.0
Requires-Dist: flask >=2.0.1
Requires-Dist: pysbd >=0.3.4
Requires-Dist: umap-learn >=0.5.1
Requires-Dist: pandas <2.0,>=1.4
Requires-Dist: matplotlib >=3.7.0
Requires-Dist: trainer >=0.0.36
Requires-Dist: coqpit >=0.0.16
Requires-Dist: jieba
Requires-Dist: pypinyin
Requires-Dist: hangul-romanize
Requires-Dist: gruut[de,es,fr] ==2.2.3
Requires-Dist: jamo
Requires-Dist: nltk
Requires-Dist: g2pkk >=0.1.1
Requires-Dist: bangla
Requires-Dist: bnnumerizer
Requires-Dist: bnunicodenormalizer
Requires-Dist: einops >=0.6.0
Requires-Dist: transformers >=4.33.0
Requires-Dist: encodec >=0.1.1
Requires-Dist: unidecode >=1.3.2
Requires-Dist: num2words
Requires-Dist: spacy[ja] >=3
Requires-Dist: black
Requires-Dist: coverage
Requires-Dist: isort
Requires-Dist: nose2
Requires-Dist: pylint ==2.10.2
Requires-Dist: bokeh ==1.4.0
Requires-Dist: mecab-python3 ==1.0.6
Requires-Dist: unidic-lite ==1.0.8
Requires-Dist: cutlet
Requires-Dist: numba ==0.55.1 ; python_version < "3.9"
Requires-Dist: numpy ==1.22.0 ; python_version <= "3.10"
Requires-Dist: numpy >=1.24.3 ; python_version > "3.10"
Requires-Dist: numba >=0.57.0 ; python_version >= "3.9"
